{
  "name": "Ace Trainer Naomi",
  "ai": "RCT",
  "battleRules": {
    "maxItemUses": 5
  },
  "bag": [
    {
      "item": "cobblemon:hyper_potion",
      "quantity": 2
    }
  ],
  "team": [
    {
      "species": "ambipom",
      "gender": "MALE",
      "level": 83,
      "nature": "jolly",
      "ability": "technician",
      "moveset": [
        "fakeout",
        "tailslap",
        "armthrust",
        "uturn"
      ],
      "ivs": {
        "hp": 31,
        "atk": 31,
        "def": 31,
        "spa": 31,
        "spd": 31,
        "spe": 31
      },
      "evs": {
        "hp": 6,
        "atk": 252,
        "spe": 252
      },
      "heldItem": "silk_scarf"
    },
    {
      "species": "bruxish",
      "gender": "MALE",
      "level": 83,
      "nature": "jolly",
      "ability": "strongjaw",
      "moveset": [
        "psychicfangs",
        "aquajet",
        "liquidation",
        "crunch"
      ],
      "ivs": {
        "hp": 31,
        "atk": 31,
        "def": 31,
        "spa": 31,
        "spd": 31,
        "spe": 31
      },
      "evs": {
        "hp": 6,
        "atk": 252,
        "spe": 252
      },
      "heldItem": "mystic_water"
    },
    {
      "species": "galvantula",
      "gender": "FEMALE",
      "level": 83,
      "nature": "timid",
      "ability": "compoundeyes",
      "moveset": [
        "bugbuzz",
        "thunder",
        "gigadrain",
        "voltswitch"
      ],
      "ivs": {
        "hp": 31,
        "atk": 31,
        "def": 31,
        "spa": 31,
        "spd": 31,
        "spe": 31
      },
      "evs": {
        "hp": 6,
        "spa": 252,
        "spe": 252
      },
      "heldItem": "magnet"
    },
    {
      "species": "shedinja",
      "gender": "GENDERLESS",
      "level": 83,
      "nature": "bashful",
      "ability": "wonderguard",
      "moveset": [
        "shadowsneak",
        "xscissor",
        "willowisp",
        "phantomforce"
      ],
      "ivs": {
        "hp": 31,
        "atk": 31,
        "def": 31,
        "spa": 31,
        "spd": 31,
        "spe": 31
      },
      "evs": {
        "hp": 4,
        "spe": 40
      },
      "heldItem": "focus_sash"
    },
    {
      "species": "absol",
      "gender": "MALE",
      "level": 84,
      "nature": "jolly",
      "ability": "pressure",
      "moveset": [
        "playrough",
        "nightslash",
        "suckerpunch",
        "superpower"
      ],
      "ivs": {
        "hp": 31,
        "atk": 31,
        "def": 31,
        "spa": 31,
        "spd": 31,
        "spe": 31
      },
      "evs": {
        "hp": 6,
        "atk": 252,
        "spe": 252
      },
      "heldItem": "expert_belt"
    }
  ]
}