{
  "name": "Artist Kevin",
  "team": [
    {
      "species": "mrmime",
      "gender": "FEMALE",
      "level": 29,
      "nature": "bold",
      "ability": "filter",
      "moveset": [
        "encore",
        "copycat",
        "pound",
        "psybeam"
      ],
      "ivs": {},
      "evs": {}
    },
    {
      "species": "sudowoodo",
      "gender": "GENDERLESS",
      "level": 29,
      "nature": "jolly",
      "ability": "rockhead",
      "moveset": [
        "flail",
        "woodhammer",
        "tearfullook",
        "suckerpunch"
      ],
      "ivs": {},
      "evs": {}
    }
  ]
}