{
  "displayName": "Biker Ruben",
  "team": [
    {
      "species": "cobblemon:accelgor",
      "gender": "MALE",
      "level": 92,
      "nature": "cobblemon:timid",
      "ability": "sheerforce",
      "moveset": [
        "uturn",
        "bugbuzz",
        "focusblast",
        "sludgebomb"
      ],
      "ivs": {
        "hp": 31,
        "attack": 31,
        "defence": 31,
        "special_attack": 31,
        "special_defence": 31,
        "speed": 31
      },
      "evs": {
        "hp": 0,
        "attack": 0,
        "defence": 0,
        "special_attack": 252,
        "special_defence": 4,
        "speed": 252
      },
      "shiny": false,
      "heldItem": "cobblemon:life_orb"
    },
    {
      "species": "cobblemon:excadrill",
      "gender": "MALE",
      "level": 93,
      "nature": "cobblemon:adamant",
      "ability": "sandrush",
      "moveset": [
        "earthquake",
        "ironhead",
        "stoneedge",
        "swordsdance"
      ],
      "ivs": {
        "hp": 31,
        "attack": 31,
        "defence": 31,
        "special_attack": 31,
        "special_defence": 31,
        "speed": 31
      },
      "evs": {
        "hp": 0,
        "attack": 252,
        "defence": 0,
        "special_attack": 0,
        "special_defence": 4,
        "speed": 252
      },
      "shiny": false,
      "heldItem": "cobblemon:air_balloon"
    },
    {
      "species": "cobblemon:gigalith",
      "gender": "MALE",
      "level": 92,
      "nature": "cobblemon:careful",
      "ability": "sandforce",
      "moveset": [
        "earthquake",
        "stoneedge",
        "explosion",
        "bodypress"
      ],
      "ivs": {
        "hp": 31,
        "attack": 31,
        "defence": 31,
        "special_attack": 31,
        "special_defence": 31,
        "speed": 31
      },
      "evs": {
        "hp": 252,
        "attack": 252,
        "defence": 0,
        "special_attack": 0,
        "special_defence": 4,
        "speed": 0
      },
      "shiny": false,
      "heldItem": "cobblemon:assault_vest"
    },
    {
      "species": "cobblemon:roserade",
      "gender": "MALE",
      "level": 92,
      "nature": "cobblemon:timid",
      "ability": "technician",
      "moveset": [
        "gigadrain",
        "weatherball",
        "hiddenpower",
        "sleeppowder"
      ],
      "ivs": {
        "hp": 31,
        "attack": 30,
        "defence": 31,
        "special_attack": 30,
        "special_defence": 31,
        "speed": 30
      },
      "evs": {
        "hp": 0,
        "attack": 252,
        "defence": 4,
        "special_attack": 0,
        "special_defence": 0,
        "speed": 252
      },
      "shiny": false,
      "heldItem": "cobblemon:lum_berry"
    },
    {
      "species": "cobblemon:lopunny",
      "gender": "FEMALE",
      "level": 93,
      "nature": "cobblemon:jolly",
      "ability": "limber",
      "moveset": [
        "fakeout",
        "return",
        "closecombat",
        "tripleaxel"
      ],
      "ivs": {
        "hp": 31,
        "attack": 31,
        "defence": 31,
        "special_attack": 31,
        "special_defence": 31,
        "speed": 31
      },
      "evs": {
        "hp": 0,
        "attack": 252,
        "defence": 4,
        "special_attack": 0,
        "special_defence": 0,
        "speed": 252
      },
      "shiny": false,
      "heldItem": "cobblemon:lopunnite"
    }
  ],
  "winCommand": "",
  "lossCommand": "",
  "canOnlyBeatOnce": false,
  "cooldownSeconds": 0
}