{
  "name": "Flint",
  "identity": "Elite Four Flint",
  "ai": {
    "type": "rct",
    "data": {
      "maxSelectMargin": 0.15
    }
  },
  "battleRules": {
    "maxItemUses": 2
  },
  "bag": [
    {
      "item": "cobblemon:full_restore",
      "quantity": 2
    }
  ],
  "team": [
    {
      "species": "houndoom",
      "gender": "GENDERLESS",
      "level": 68,
      "nature": "modest",
      "ability": "unnerve",
      "moveset": [
        "flamethrower",
        "darkpulse",
        "destinybond",
        "nastyplot"
      ],
      "ivs": {
        "hp": 31,
        "def": 31,
        "spa": 31,
        "spd": 31,
        "spe": 31
      },
      "evs": {
        "hp": 52,
        "spa": 252,
        "spe": 204
      },
      "heldItem": "wise_glasses"
    },
    {
      "species": "flareon",
      "gender": "MALE",
      "level": 71,
      "nature": "adamant",
      "ability": "flashfire",
      "moveset": [
        "flareblitz",
        "flail",
        "willowisp",
        "quickattack"
      ],
      "ivs": {
        "hp": 31,
        "atk": 31,
        "def": 31,
        "spd": 31,
        "spe": 31
      },
      "evs": {
        "hp": 252,
        "atk": 252
      },
      "heldItem": "sitrus_berry"
    },
    {
      "species": "rapidash",
      "gender": "GENDERLESS",
      "level": 69,
      "nature": "jolly",
      "ability": "flamebody",
      "moveset": [
        "flareblitz",
        "irontail",
        "poisonjab",
        "hypnosis"
      ],
      "ivs": {
        "hp": 31,
        "atk": 31,
        "def": 31,
        "spd": 31,
        "spe": 31
      },
      "evs": {
        "hp": 52,
        "atk": 252,
        "spe": 204
      },
      "heldItem": "wide_lens"
    },
    {
      "species": "infernape",
      "gender": "FEMALE",
      "level": 71,
      "nature": "jolly",
      "ability": "ironfist",
      "moveset": [
        "firepunch",
        "thunderpunch",
        "closecombat",
        "machpunch"
      ],
      "ivs": {
        "hp": 31,
        "atk": 31,
        "def": 31,
        "spd": 31,
        "spe": 31
      },
      "evs": {
        "hp": 52,
        "atk": 252,
        "spe": 204
      },
      "heldItem": "focus_sash"
    },
    {
      "species": "magmortar",
      "gender": "GENDERLESS",
      "level": 73,
      "nature": "modest",
      "ability": "flamebody",
      "moveset": [
        "fireblast",
        "thunderbolt",
        "focusblast",
        "psychic"
      ],
      "ivs": {
        "hp": 31,
        "def": 31,
        "spa": 31,
        "spd": 31,
        "spe": 31
      },
      "evs": {
        "hp": 52,
        "spa": 252,
        "spe": 204
      },
      "heldItem": "lum_berry"
    }
  ]
}