{
  "name": "Expert Kenlawa",
  "ai": {
    "type": "rct",
    "data": {
      "maxSelectMargin": 0.15
    }
  },
  "battleRules": {
    "maxItemUses": 4
  },
  "bag": [
    {
      "item": "cobblemon:superb_remedy",
      "quantity": 2
    }
  ],
  "team": [
    {
      "species": "mimikyu",
      "gender": "FEMALE",
      "level": 81,
      "nature": "adamant",
      "ability": "disguise",
      "moveset": [
        "playrough",
        "taunt",
        "lightscreen",
        "protect"
      ],
      "ivs": {
        "hp": 31,
        "atk": 31,
        "def": 31,
        "spa": 31,
        "spd": 31,
        "spe": 31
      },
      "evs": {
        "hp": 6,
        "atk": 252,
        "spd": 252
      },
      "heldItem": "light_clay"
    }
  ]
}