{
  "name": "Ninja Boy Zach",
  "team": [
    {
      "species": "golbat",
      "gender": "GENDERLESS",
      "level": 36,
      "nature": "jolly",
      "ability": "innerfocus",
      "moveset": [
        "screech",
        "poisonfang",
        "aircutter",
        "bite"
      ],
      "ivs": {},
      "evs": {}
    },
    {
      "species": "golbat",
      "gender": "MALE",
      "level": 37,
      "nature": "jolly",
      "ability": "innerfocus",
      "moveset": [
        "screech",
        "poisonfang",
        "aircutter",
        "bite"
      ],
      "ivs": {},
      "evs": {}
    },
    {
      "species": "golbat",
      "gender": "FEMALE",
      "level": 38,
      "nature": "timid",
      "ability": "innerfocus",
      "moveset": [
        "astonish",
        "poisonfang",
        "aircutter",
        "bite"
      ],
      "ivs": {},
      "evs": {}
    }
  ]
}