{
  "name": "Picnicker Becky",
  "team": [
    {
      "species": "raichu",
      "gender": "MALE",
      "level": 54,
      "nature": "mild",
      "ability": "static",
      "moveset": [
        "tailwhip",
        "quickattack",
        "thunderbolt",
        "extremespeed"
      ],
      "ivs": {
        "hp": 5,
        "atk": 5,
        "def": 5,
        "spa": 5,
        "spd": 5,
        "spe": 5
      },
      "evs": {}
    },
    {
      "species": "raichu",
      "gender": "MALE",
      "level": 54,
      "nature": "relaxed",
      "ability": "static",
      "moveset": [
        "tailwhip",
        "quickattack",
        "thunderbolt",
        "extremespeed"
      ],
      "ivs": {
        "hp": 5,
        "atk": 5,
        "def": 5,
        "spa": 5,
        "spd": 5,
        "spe": 5
      },
      "evs": {}
    }
  ]
}