{
  "name": "Pokémon Trainer Cedric",
  "ai": {
    "type": "rct",
    "data": {
      "maxSelectMargin": 0.15
    }
  },
  "battleRules": {
    "maxItemUses": 2
  },
  "bag": [
    {
      "item": "cobblemon:super_potion",
      "quantity": 1
    }
  ],
  "team": [
    {
      "species": "starly",
      "gender": "MALE",
      "level": 19,
      "nature": "jolly",
      "ability": "keeneye",
      "moveset": [
        "quickattack",
        "doubleteam",
        "endeavor",
        "pluck"
      ],
      "ivs": {
        "hp": 5,
        "atk": 5,
        "def": 5,
        "spa": 5,
        "spd": 5,
        "spe": 5
      },
      "evs": {
        "hp": 12,
        "atk": 28,
        "def": 4,
        "spd": 4,
        "spe": 12
      }
    },
    {
      "species": "buizel",
      "gender": "FEMALE",
      "level": 20,
      "nature": "jolly",
      "ability": "swiftswim",
      "moveset": [
        "tailwhip",
        "quickattack",
        "watergun",
        "bite"
      ],
      "ivs": {
        "hp": 6,
        "atk": 6,
        "def": 6,
        "spa": 6,
        "spd": 6,
        "spe": 6
      },
      "evs": {
        "atk": 28,
        "def": 4,
        "spd": 4,
        "spe": 12
      }
    },
    {
      "species": "ponyta",
      "gender": "MALE",
      "level": 20,
      "nature": "jolly",
      "ability": "flashfire",
      "moveset": [
        "tackle",
        "tailwhip",
        "flamecharge",
        "agility"
      ],
      "ivs": {
        "hp": 7,
        "atk": 7,
        "def": 7,
        "spa": 7,
        "spd": 7,
        "spe": 7
      },
      "evs": {
        "atk": 28,
        "def": 4,
        "spd": 4,
        "spe": 12
      }
    },
    {
      "species": "grotle",
      "gender": "MALE",
      "level": 21,
      "nature": "careful",
      "ability": "overgrow",
      "moveset": [
        "absorb",
        "razorleaf",
        "curse",
        "stealthrock"
      ],
      "ivs": {
        "hp": 11,
        "atk": 11,
        "def": 11,
        "spa": 11,
        "spd": 11,
        "spe": 11
      },
      "evs": {
        "hp": 36,
        "atk": 4,
        "def": 12,
        "spa": 4,
        "spd": 36
      }
    }
  ]
}