{
  "displayName": "Sailor Trevor",
  "team": [
    {
      "species": "cobblemon:cramorant",
      "gender": "FEMALE",
      "level": 89,
      "nature": "cobblemon:timid",
      "ability": "gulpmissile",
      "moveset": [
        "surf",
        "uturn",
        "airslash",
        "safeguard"
      ],
      "ivs": {
        "hp": 31,
        "attack": 31,
        "defence": 31,
        "special_attack": 31,
        "special_defence": 31,
        "speed": 31
      },
      "evs": {
        "hp": 0,
        "attack": 0,
        "defence": 0,
        "special_attack": 0,
        "special_defence": 0,
        "speed": 0
      },
      "shiny": false,
      "heldItem": "cobblemon:focus_sash"
    },
    {
      "species": "cobblemon:nidoqueen",
      "gender": "FEMALE",
      "level": 90,
      "nature": "cobblemon:timid",
      "ability": "sheerforce",
      "moveset": [
        "surf",
        "scorchingsands",
        "sludge",
        "reflect"
      ],
      "ivs": {
        "hp": 31,
        "attack": 31,
        "defence": 31,
        "special_attack": 31,
        "special_defence": 31,
        "speed": 31
      },
      "evs": {
        "hp": 0,
        "attack": 0,
        "defence": 0,
        "special_attack": 0,
        "special_defence": 0,
        "speed": 0
      },
      "shiny": false,
      "heldItem": "cobblemon:none"
    }
  ],
  "winCommand": "",
  "lossCommand": "",
  "canOnlyBeatOnce": false,
  "cooldownSeconds": 0
}