{
  "name": "Swimmer♀ Amara",
  "team": [
    {
      "species": "milotic",
      "gender": "MALE",
      "level": 93,
      "nature": "modest",
      "ability": "competitive",
      "moveset": [
        "hydropump",
        "icebeam",
        "hiddenpower",
        "haze"
      ],
      "ivs": {
        "hp": 31,
        "atk": 30,
        "def": 31,
        "spa": 30,
        "spd": 31,
        "spe": 31
      },
      "evs": {
        "hp": 252,
        "def": 4,
        "spa": 252
      },
      "heldItem": "sitrus_berry"
    },
    {
      "species": "milotic",
      "gender": "FEMALE",
      "level": 92,
      "nature": "modest",
      "ability": "serenegrace",
      "moveset": [
        "scorchingsands",
        "moonblast",
        "scald",
        "recover"
      ],
      "ivs": {
        "hp": 31,
        "atk": 31,
        "def": 31,
        "spa": 31,
        "spd": 31,
        "spe": 31
      },
      "evs": {
        "hp": 252,
        "def": 4,
        "spa": 252
      },
      "heldItem": "leftovers",
      "aspects": [
        "sevii"
      ]
    },
    {
      "species": "dewgong",
      "gender": "FEMALE",
      "level": 92,
      "nature": "calm",
      "ability": "icescales",
      "moveset": [
        "scald",
        "icebeam",
        "rest",
        "sleeptalk"
      ],
      "ivs": {
        "hp": 31,
        "atk": 31,
        "def": 31,
        "spa": 31,
        "spd": 31,
        "spe": 31
      },
      "evs": {
        "hp": 252,
        "def": 4,
        "spe": 252
      },
      "heldItem": "sitrus_berry"
    }
  ]
}