{
  "name": "Team Rocket Grunt",
  "identity": "Team Rocket Grunt (8)",
  "team": [
    {
      "species": "rattata",
      "gender": "MALE",
      "level": 16,
      "nature": "bashful",
      "ability": "hustle",
      "moveset": [
        "quickattack",
        "focusenergy",
        "hyperfang",
        "pursuit"
      ],
      "ivs": {
        "hp": 15,
        "atk": 15,
        "def": 15,
        "spa": 15,
        "spd": 15,
        "spe": 15
      },
      "evs": {},
      "aspects": [
        "alolan"
      ]
    },
    {
      "species": "silicobra",
      "gender": "MALE",
      "level": 17,
      "nature": "sassy",
      "ability": "shedskin",
      "moveset": [
        "glare",
        "brutalswing",
        "rocktomb",
        "bulldoze"
      ],
      "ivs": {
        "hp": 15,
        "atk": 15,
        "def": 15,
        "spa": 15,
        "spd": 15,
        "spe": 15
      },
      "evs": {}
    }
  ]
}