{
  "name": "Youngster Timmy",
  "team": [
    {
      "species": "raticate",
      "gender": "MALE",
      "level": 52,
      "nature": "mild",
      "ability": "guts",
      "moveset": [
        "return",
        "superfang",
        "doubleedge",
        "endeavor"
      ],
      "ivs": {
        "hp": 5,
        "atk": 5,
        "def": 5,
        "spa": 5,
        "spd": 5,
        "spe": 5
      },
      "evs": {}
    },
    {
      "species": "arbok",
      "gender": "MALE",
      "level": 52,
      "nature": "hasty",
      "ability": "shedskin",
      "moveset": [
        "coil",
        "jawlock",
        "belch",
        "haze"
      ],
      "ivs": {
        "hp": 5,
        "atk": 5,
        "def": 5,
        "spa": 5,
        "spd": 5,
        "spe": 5
      },
      "evs": {}
    },
    {
      "species": "golbat",
      "gender": "FEMALE",
      "level": 52,
      "nature": "naughty",
      "ability": "sniper",
      "moveset": [
        "haze",
        "venoshock",
        "airslash",
        "quickguard"
      ],
      "ivs": {
        "hp": 5,
        "atk": 5,
        "def": 5,
        "spa": 5,
        "spd": 5,
        "spe": 5
      },
      "evs": {}
    }
  ]
}